bluecast/__init__.py
bluecast/blueprints/__init__.py
bluecast/blueprints/cast.py
bluecast/blueprints/cast_cv.py
bluecast/blueprints/cast_cv_regression.py
bluecast/blueprints/cast_regression.py
bluecast/blueprints/custom_model_recipes.py
bluecast/blueprints/orchestration.py
bluecast/blueprints/preprocessing_recipes.py
bluecast/blueprints/welcome.py
bluecast/config/__init__.py
bluecast/config/base_classes.py
bluecast/config/training_config.py
bluecast/conformal_prediction/__init__.py
bluecast/conformal_prediction/base_classes.py
bluecast/conformal_prediction/conformal_prediction.py
bluecast/conformal_prediction/conformal_prediction_regression.py
bluecast/conformal_prediction/effectiveness_nonconformity_measures.py
bluecast/conformal_prediction/evaluation.py
bluecast/conformal_prediction/nonconformity_measures.py
bluecast/conformal_prediction/nonconformity_measures_regression.py
bluecast/eda/__init__.py
bluecast/eda/analyse.py
bluecast/eda/data_leakage_checks.py
bluecast/evaluation/__init__.py
bluecast/evaluation/base_classes.py
bluecast/evaluation/error_analysis.py
bluecast/evaluation/error_analysis_regression.py
bluecast/evaluation/eval_metrics.py
bluecast/evaluation/shap_values.py
bluecast/experimentation/__init__.py
bluecast/experimentation/tracking.py
bluecast/general_utils/__init__.py
bluecast/general_utils/general_utils.py
bluecast/ml_modelling/__init__.py
bluecast/ml_modelling/base_classes.py
bluecast/ml_modelling/parameter_tuning_utils.py
bluecast/ml_modelling/xgboost.py
bluecast/ml_modelling/xgboost_regression.py
bluecast/monitoring/__init__.py
bluecast/monitoring/data_monitoring.py
bluecast/preprocessing/.ipynb_checkpoints/feature_selection-checkpoint.py
bluecast/preprocessing/__init__.py
bluecast/preprocessing/category_encoder_orchestration.py
bluecast/preprocessing/custom.py
bluecast/preprocessing/datetime_features.py
bluecast/preprocessing/encode_target_labels.py
bluecast/preprocessing/feature_creation.py
bluecast/preprocessing/feature_selection.py
bluecast-1.6.4.dist-info/LICENSE
bluecast-1.6.4.dist-info/METADATA
bluecast-1.6.4.dist-info/WHEEL
bluecast-1.6.4.dist-info/RECORD
