Metadata-Version: 2.1
Name: bluecast
Version: 1.6.4
Summary: A lightweight and fast automl framework
Home-page: https://github.com/ThomasMeissnerDS/BlueCast
License: GPL-3.0-only
Author: Thomas Meißner
Author-email: meissnercorporation@gmx.de
Requires-Python: >=3.9,<3.13
Classifier: License :: OSI Approved :: GNU General Public License v3 (GPLv3)
Classifier: Programming Language :: Python :: 3
Classifier: Programming Language :: Python :: 3.9
Classifier: Programming Language :: Python :: 3.10
Classifier: Programming Language :: Python :: 3.11
Classifier: Programming Language :: Python :: 3.12
Provides-Extra: full
Provides-Extra: jupyter
Requires-Dist: category_encoders (>=2.3.0,<3.0.0)
Requires-Dist: dill (>=0.3.3,<0.4.0)
Requires-Dist: matplotlib (>=3.1.3)
Requires-Dist: numpy (<2.0.0)
Requires-Dist: optuna (>=2.8.0)
Requires-Dist: optuna-integration (>=3.0)
Requires-Dist: pandas (>=1.1.5)
Requires-Dist: plotly (>=5,<6)
Requires-Dist: polars (>=0.20.0,!=1.7.0)
Requires-Dist: pyarrow (>=10.0.0)
Requires-Dist: pydantic (>=1.1.0)
Requires-Dist: s3fs (>=2022.1.0)
Requires-Dist: scikit-learn (>=1.0.1)
Requires-Dist: seaborn (>=0.10.0)
Requires-Dist: shap (>=0.44.1)
Requires-Dist: xgboost (<2.2.0)
Project-URL: Repository, https://github.com/ThomasMeissnerDS/BlueCast
